bechdel_corpus/__init__.py
bechdel_corpus/example.py
bechdel_corpus-0.0.1.dist-info/METADATA
bechdel_corpus-0.0.1.dist-info/WHEEL
bechdel_corpus-0.0.1.dist-info/top_level.txt
bechdel_corpus-0.0.1.dist-info/RECORD
